syncasync.py
syncasync-20180812.dist-info/METADATA
syncasync-20180812.dist-info/RECORD
syncasync-20180812.dist-info/WHEEL
syncasync-20180812.dist-info/top_level.txt
